LICENSE
MANIFEST.in
setup.cfg
setup.py
Testwa_Python_Client.egg-info/PKG-INFO
Testwa_Python_Client.egg-info/SOURCES.txt
Testwa_Python_Client.egg-info/dependency_links.txt
Testwa_Python_Client.egg-info/requires.txt
Testwa_Python_Client.egg-info/top_level.txt
docs/roadmap.md
testwa/__init__.py
testwa/saucetestcase.py
testwa/common/__init__.py
testwa/common/exceptions.py
testwa/webdriver/__init__.py
testwa/webdriver/connectiontype.py
testwa/webdriver/errorhandler.py
testwa/webdriver/mobilecommand.py
testwa/webdriver/switch_to.py
testwa/webdriver/webdriver.py
testwa/webdriver/webelement.py
testwa/webdriver/common/__init__.py
testwa/webdriver/common/mobileby.py
testwa/webdriver/common/multi_action.py
testwa/webdriver/common/touch_action.py